gwx_telehealth/__init__.py
gwx_telehealth/abstract_telehealth_service.py
gwx_telehealth/provider_service.py
gwx_telehealth/config/__init__.py
gwx_telehealth/config/gwx_telehealth_config.ini
gwx_telehealth/providers/__init__.py
gwx_telehealth/providers/coviu_service.py
gwx_telehealth/services/__init__.py
gwx_telehealth/services/auth_service.py
gwx_telehealth/services/config_parser_service.py
gwx_telehealth/services/service_locator_service.py
gwx_telehealth/tokens/__init__.py
gwx_telehealth-0.0.7.dist-info/LICENSE
gwx_telehealth-0.0.7.dist-info/METADATA
gwx_telehealth-0.0.7.dist-info/WHEEL
gwx_telehealth-0.0.7.dist-info/top_level.txt
gwx_telehealth-0.0.7.dist-info/RECORD
