Metadata-Version: 2.1
Name: gwx-telehealth
Version: 0.0.7
Summary: Adapter for telehealth systems API integration
Home-page: UNKNOWN
Author: Jerric Calosor
Author-email: jerric.calosor@groworx.com.au
License: UNKNOWN
Platform: UNKNOWN
Classifier: Programming Language :: Python :: 3
Classifier: License :: OSI Approved :: MIT License
Classifier: Operating System :: OS Independent
Requires-Python: >=3.7
